auwiwftaaa/__init__.py
auwiwftaaa/__main__.py
auwiwftaaa/color.py
auwiwftaaa/config.py
auwiwftaaa/start.py
abbreviation_uhh_what_is_word_for_tearing_apart_an_abbreviation-2.3.0.dist-info/LICENSE
abbreviation_uhh_what_is_word_for_tearing_apart_an_abbreviation-2.3.0.dist-info/METADATA
abbreviation_uhh_what_is_word_for_tearing_apart_an_abbreviation-2.3.0.dist-info/WHEEL
abbreviation_uhh_what_is_word_for_tearing_apart_an_abbreviation-2.3.0.dist-info/top_level.txt
abbreviation_uhh_what_is_word_for_tearing_apart_an_abbreviation-2.3.0.dist-info/RECORD
