Metadata-Version: 2.1
Name: abbreviation-uhh-what-is-word-for-tearing-apart-an-abbreviation
Version: 2.3.0
Summary: no, this page doesn't exist
Author: sqdnoises
License: The MIT License (MIT)        
Classifier: Programming Language :: Python :: 3
Classifier: License :: OSI Approved :: MIT License
Classifier: Operating System :: OS Independent
Requires-Python: >=3.8
License-File: LICENSE
